diskwrangler/Analyzer.py
diskwrangler/BamDialog.py
diskwrangler/BamModel.py
diskwrangler/BamTable.py
diskwrangler/C64_Pro_Mono-STYLE.ttf
diskwrangler/DirTableModel.py
diskwrangler/DiskWrangler.py
diskwrangler/FontDialog.py
diskwrangler/GeoPaintDialog.py
diskwrangler/HexDialog.py
diskwrangler/HexModel.py
diskwrangler/HexTable.py
diskwrangler/PhotoScrapDialog.py
diskwrangler/PlaintextDialog.py
diskwrangler/SearchDialog.py
diskwrangler/Searcher.py
diskwrangler/SectorErrorDialog.py
diskwrangler/SectorErrorModel.py
diskwrangler/SectorErrorTable.py
diskwrangler/__init__.py
diskwrangler/__main__.py
diskwrangler/separator.png
diskwrangler/wizard-icon.png
diskwrangler-3.3.1.dist-info/licenses/LICENSE
diskwrangler-3.3.1.dist-info/METADATA
diskwrangler-3.3.1.dist-info/WHEEL
diskwrangler-3.3.1.dist-info/top_level.txt
diskwrangler-3.3.1.dist-info/RECORD
